tools_smawe/__init__.py
tools_smawe/__version__.py
tools_smawe/settings.py
tools_smawe/tool.py
tools_smawe/exception/__init__.py
tools_smawe/net/__init__.py
tools_smawe/retrying/__init__.py
tools_smawe/retrying/retry.py
tools_smawe-0.2.0.dist-info/LICENSE
tools_smawe-0.2.0.dist-info/METADATA
tools_smawe-0.2.0.dist-info/WHEEL
tools_smawe-0.2.0.dist-info/top_level.txt
tools_smawe-0.2.0.dist-info/RECORD
