Metadata-Version: 2.1
Name: tools-smawe
Version: 0.2.0
Summary: small tool
Author: Samwe
Author-email: 1281722462@qq.com
License: MIT
Classifier: License :: OSI Approved :: MIT License
Classifier: Programming Language :: Python :: 3
Classifier: Programming Language :: Python :: Implementation :: CPython
Classifier: Programming Language :: Python :: Implementation :: PyPy
Requires-Python: >=3.5.0
License-File: LICENSE
Requires-Dist: retrying
Requires-Dist: colorama
